auth_parser/__init__.py
auth_parser/parser.py
auth_parser_AAA-0.1.0.dist-info/LICENSE
auth_parser_AAA-0.1.0.dist-info/METADATA
auth_parser_AAA-0.1.0.dist-info/WHEEL
auth_parser_AAA-0.1.0.dist-info/top_level.txt
auth_parser_AAA-0.1.0.dist-info/RECORD
