Metadata-Version: 2.1
Name: auth_parser_AAA
Version: 0.1.0
Summary: A simple User-Agent string parser.
Author-email: Your Name <your.email@example.com>
License: MIT
Requires-Python: >=3.6
License-File: LICENSE
Requires-Dist: ua-parser
